<annotation>
	<folder>down</folder>
	<filename>EYE DOWN_80.jpg</filename>
	<path>C:\Users\balav\OneDrive\Dokumen\Desktop\New folder\down\EYE DOWN_80.jpg</path>
	<source>
		<database>Unknown</database>
	</source>
	<size>
		<width>4624</width>
		<height>3472</height>
		<depth>3</depth>
	</size>
	<segmented>0</segmented>
	<object>
		<name>EYE DOWN</name>
		<pose>Unspecified</pose>
		<truncated>0</truncated>
		<difficult>0</difficult>
		<bndbox>
			<xmin>1277</xmin>
			<ymin>922</ymin>
			<xmax>2591</xmax>
			<ymax>1849</ymax>
		</bndbox>
	</object>
	<object>
		<name>EYE DOWN</name>
		<pose>Unspecified</pose>
		<truncated>0</truncated>
		<difficult>0</difficult>
		<bndbox>
			<xmin>2900</xmin>
			<ymin>913</ymin>
			<xmax>3896</xmax>
			<ymax>1840</ymax>
		</bndbox>
	</object>
</annotation>
